verilog数字VLSI设计教程/Lab01/Lab01_Ans/XorNor.v
// ===========================================================
// XorNor:   Combinational logic using ^ and ~|.
// This module represents simple combinational logic including
// an XOR and a NOR expression.
//
// ANSI module header.
// ------------------------------------------------------------
// 2005-04-09 jmw: v. 1.1 modified comment on wire declarations.
// 2004-11-25 jmw: v. 1.0 implemented.
// ============================================================
module XorNor (output X, Y, input A, B, C);
  wire x; // To illustrate use of internal wiring.
  //
  assign #1 X = x;
  //
  assign #10 x = A ^ B;
  assign #10 Y = ~(x | C);
  //
endmodule // XorNor

verilog数字VLSI设计教程/Lab01/SR.v
// ===========================================================
// SR:  An S-R Latch using ~ and &.
// This module represents the functionality of a simple latch,
// which is a sequential logic device, using combinational 
// ~AND expressions connected to feed back on each other.
//
// ANSI module header.
// ------------------------------------------------------------
// 2005-04-09 jmw: v. 1.1 modified comment on wire declarations.
// 2004-11-25 jmw: v. 1.0 implemented.
// ============================================================
module SR (output Q, Qn, input S, R);
  wire q, qn;  // Internal wiring.
  //
  assign #1 Q  = q;
  assign #1 Qn = qn;
  //
  assign #10 q  = ~(S & qn);
  assign #10 qn = ~(R & q );
  //
endmodule // SR

verilog数字VLSI设计教程/Lab05/Lab05_Ans/04_MuxInserted/AndOr.v
// ===========================================================
// AndOr:   Combinational logic module.
//
// ------------------------------------------------------------
// 2004-12-08 jmw:  v. 1.0 of AndOr implemented by copying
//            from Lab01.
// 2004-11-25 jmw:  v. 1.0 implemented.
// ============================================================
module AndOr (output X, Y, input A, B, C);
  assign #10 X = A & B;
  assign #10 Y = B | C;
endmodule

verilog数字VLSI设计教程/Lab01/Intro_Top.v
// ===========================================================
// Intro_Top:  Top level of a simple design using
// verilog continuous assignment statements.
//
// This module contains the top structure of the design, which
// is made up of three lower-level modules and one inverter gate.
// The structure is represented by module instances.
//
// All ports are wire types, because this is the default; also,
// there is no storage of state in combinational statements.
//
// ANSI module header.
// ------------------------------------------------------------
// 2005-09-20 jmw: v. 1.1 Comment modified.
// 2004-11-25 jmw: v. 1.0 implemented.
// ============================================================
module Intro_Top (output X, Y, Z, input A, B, C, D);
  //
  wire ab, bc, q, qn;  // Wires for internal connectivity.
  //
  // Implied wires may be assumed in this combinational 
  // design, when connecting declared ports to instance ports.
  // The #1 is a delay time, in `timescale units:
  //
  assign #1 Z = ~qn; // Inverter by continuous assignment statement.
  //
   AndOr InputCombo01  (.X(ab), .Y(bc), .A(A), .B(B), .C(C));
      SR SRLatch01     (.Q(q), .Qn(qn), .S(bc), .R(D));
  XorNor OutputCombo01 (.X(X), .Y(Y), .A(ab), .B(q), .C(qn));
  //
endmodule // Intro_Top.

verilog数字VLSI设计教程/Lab01/Lab01_Ans/TestBench.v
// ===========================================================
// TestBench:  Simulation driver module (stimulus block) 
// for the top-level block instance of Intro_Top.
//
// This module includes an initial block which assigns various
// values to top-level inputs for simulation.   initial blocks
// are ignored in logic synthesis.
//
// No module port declaration.
// ------------------------------------------------------------
// 2004-11-25 jmw: v. 1.0 implemented.
// ============================================================
//
`timescale 1 ns/100ps   // No semicolon after `(anything).
//
module TestBench;    // Stimulus blocks have no port.
//
reg  Astim, Bstim, Cstim, Dstim;  // To accept initialization.
wire Xwatch, Ywatch, Zwatch;      // To connect to design instance.
//
initial
  begin
`include "../../VCS/Extras.inc"
  //
  // Each '#' precedes a delay time, here in 1 ns units:
  //
  #1  Astim = 1'b0;   // For Astim, 1 bit, representing a binary 0.
  #1  Bstim = 1'b0;
  #1  Cstim = 1'b0;
  #1  Dstim = 1'b0;
  #50 Astim = 1'b1;
  #50 Bstim = 1'b1;
  #50 Cstim = 1'b1;
  #50 Dstim = 1'b1;
  #50 Bstim = 1'b0;
  #50 Dstim = 1'b0;
  #50 Dstim = 1'b1;
  #50 Astim = 1'b0;
  #50 Cstim = 1'b0;
  #50 Dstim = 1'b0;
  #50 $finish;       // Terminates simulation.
  end // No semicolon after end.
//
// The instance of the design is named Topper01, and its
// ports are associated by name with stimulus input and simulation
// output wires:
//
Intro_Top Topper01 ( .X(Xwatch), .Y(Ywatch), .Z(Zwatch)
                   , .A(Astim),  .B(Bstim),  .C(Cstim), .D(Dstim)
                   );
//
endmodule // TestBench.

verilog数字VLSI设计教程/Lab01/Lab01_Ans/VCS_SimRun.VCD
$date
	Mon Nov 19 12:46:18 2007
$end

$version
	Synopsys VCS version Y-2006.06-SP1
$end

$timescale
	100ps
$end

$comment Csum: 1 03163cd59e3f0ec1 $end


$scope module TestBench $end
$var reg 1 ! Astim $end
$var reg 1 " Bstim $end
$var reg 1 # Cstim $end
$var reg 1 $ Dstim $end
$var wire 1 % Xwatch $end
$var wire 1 & Ywatch $end
$var wire 1 ' Zwatch $end

$scope module Topper01 $end
$var wire 1 % X $end
$var wire 1 & Y $end
$var wire 1 ' Z $end
$var wire 1 ! A $end
$var wire 1 " B $end
$var wire 1 # C $end
$var wire 1 $ D $end
$var wire 1 ( ab $end
$var wire 1 ) bc $end
$var wire 1 * q $end
$var wire 1 + qn $end

$scope module InputCombo01 $end
$var wire 1 ( X $end
$var wire 1 ) Y $end
$var wire 1 ! A $end
$var wire 1 " B $end
$var wire 1 # C $end
$upscope $end


$scope module SRLatch01 $end
$var wire 1 * Q $end
$var wire 1 + Qn $end
$var wire 1 ) S $end
$var wire 1 $ R $end
$var wire 1 , q $end
$var wire 1 - qn $end
$upscope $end


$scope module OutputCombo01 $end
$var wire 1 % X $end
$var wire 1 & Y $end
$var wire 1 ( A $end
$var wire 1 * B $end
$var wire 1 + C $end
$var wire 1 . x $end
$upscope $end

$upscope $end

$upscope $end

$enddefinitions $end

#0
$dumpvars
x!
x"
x#
x$
x%
x&
x*
x+
x,
x-
x(
x)
x'
x.
$end
#10
0!
#20
0"
#30
0#
#40
0$
#110
0(
#130
0)
#140
1-
#150
1+
#160
0'
#230
1,
#240
1*
#250
0&
#340
1.
#350
1%
#540
1!
#1040
1"
#1140
1)
1(
#1240
0,
0.
#1250
0*
0%
#1350
1.
#1360
1%
#1540
1#
#2040
1$
#2540
0"
#2640
0(
#2740
0.
#2750
0%
#3040
0$
#3540
1$
#4040
0!
#4540
0#
#4640
0)
#4740
1,
#4750
1*
#4840
0-
#4850
1.
0+
#4860
1%
1'
#5040
0$
#5140
1-
#5150
1+
#5160
0'
